jx_bigquery
jx_bigquery/expressions
